LICENSE
README.md
setup.cfg
setup.py
src/fb_waba_manager/__init__.py
src/fb_waba_manager/fb_waba_manager.py
src/fb_waba_manager.egg-info/PKG-INFO
src/fb_waba_manager.egg-info/SOURCES.txt
src/fb_waba_manager.egg-info/dependency_links.txt
src/fb_waba_manager.egg-info/requires.txt
src/fb_waba_manager.egg-info/top_level.txt
src/fb_waba_manager/constants/__init__.py
src/fb_waba_manager/constants/facebook/__init__.py
src/fb_waba_manager/constants/facebook/fb_constants.py
src/fb_waba_manager/constants/http/__init__.py
src/fb_waba_manager/constants/http/methods_constants.py
src/fb_waba_manager/factories/__init__.py
src/fb_waba_manager/factories/facebook/__init__.py
src/fb_waba_manager/factories/facebook/graph_api_factory.py
src/fb_waba_manager/services/__init__.py
src/fb_waba_manager/services/facebook/__init__.py
src/fb_waba_manager/services/facebook/whatsapp/__init__.py
src/fb_waba_manager/services/facebook/whatsapp/waba_service.py
src/fb_waba_manager/sessions/__init__.py
src/fb_waba_manager/sessions/facebook/__init__.py
src/fb_waba_manager/sessions/facebook/graph_api_session.py