Metadata-Version: 2.1
Name: fb-waba-manager
Version: 0.0.4
Summary: Helper to handle with facebook's waba
Home-page: https://github.com/chr0m1ng/fb-waba-manager
Author: Gabriel Rodrigues dos Santos
Author-email: gabrielr@take.net
License: MIT
Keywords: facebook,graph api,waba
Platform: UNKNOWN
Classifier: Development Status :: 4 - Beta
Classifier: Intended Audience :: Developers
Classifier: Topic :: Software Development :: Build Tools
Classifier: License :: OSI Approved :: MIT License
Classifier: Programming Language :: Python :: 3.5
Classifier: Programming Language :: Python :: 3.6
Classifier: Programming Language :: Python :: 3.7
Classifier: Programming Language :: Python :: 3.8
